main.py
adb_mcp_server-1.0.0.dist-info/METADATA
adb_mcp_server-1.0.0.dist-info/WHEEL
adb_mcp_server-1.0.0.dist-info/entry_points.txt
adb_mcp_server-1.0.0.dist-info/top_level.txt
adb_mcp_server-1.0.0.dist-info/RECORD
