Metadata-Version: 2.4
Name: adb-mcp-server
Version: 1.0.0
Summary: A server implementation for handling ADB (Android Debug Bridge) communications using the Message Control Protocol (MCP)
Requires-Python: >=3.12
Requires-Dist: mcp>=1.6.0
